taginfo/__init__.py
taginfo/analysis.py
taginfo/query.py
taginfo-0.0.5.dist-info/licenses/LICENSE
taginfo-0.0.5.dist-info/METADATA
taginfo-0.0.5.dist-info/WHEEL
taginfo-0.0.5.dist-info/top_level.txt
taginfo-0.0.5.dist-info/RECORD
