Metadata-Version: 2.4
Name: taginfo
Version: 0.0.5
Summary: A small wrapper around taginfo API
Home-page: https://github.com/matkoniecz/taginfo_api_wrapper_in_python
Author: Mateusz Konieczny
License: MIT
Classifier: Programming Language :: Python :: 3
Classifier: Operating System :: OS Independent
License-File: LICENSE
Requires-Dist: osm_bot_abstraction_layer
Dynamic: author
Dynamic: classifier
Dynamic: description
Dynamic: description-content-type
Dynamic: home-page
Dynamic: license
Dynamic: license-file
Dynamic: requires-dist
Dynamic: summary
